{"code":0,"message":"0","ttl":1,"data":{"item_id":40665,"name":"蛋酒一家","group_id":46,"group_name":"蛋酒一家","part_id":6,"state":"active","properties":{"desc":"咿呀咿呀蛋酒一家！本套装包括动态卡片和表情包，永久购买还能成为认证粉丝，领取粉丝专属装扮！","fan_desc":"蛋酒一家","fan_id":"蛋酒一家","fan_item_ids":"40662,40588,40635,40637","fan_mid":"504406727","fan_no_color":"#21abea","fan_recommend_desc":"咿呀咿呀蛋酒一家，我们的故事一直在继续哦！","fan_recommend_jump_type":"url","fan_recommend_jump_value":"https://www.bilibili.com/video/BV1z24y1y7zA/?spm_id_from=333.999.list.card_archive.click\u0026vd_source=c706d7e3cff5a94abff3210810ca46cf","fan_share_image":"https://i0.hdslb.com/bfs/garb/item/f9a0ef726478820446cc54d7cf96ba894eedd4b6.jpg","gray_rule":"false","image_cover":"https://i0.hdslb.com/bfs/garb/item/7f4aa66794a7c4b9f4f99a3fd0ba6beb96877f51.jpg","image_cover_color":"#a16fef","is_hide":"false","item_id_card":"40587","item_id_emoji":"40595","rank_investor_show":"false","realname_auth":"false","sale_bp_forever_raw":"3500","sale_bp_pm_raw":"800","sale_buy_num_limit":"100","sale_quantity":"19999","sale_quantity_limit":"true","sale_region_ip_limit":"全球","sale_reserve_switch":"true","sale_time_begin":"1668931200","sale_type":"pay","suit_card_type":"big_img","type":"ip"},"current_activity":{"type":"discount","time_limit":true,"time_left":411355,"tag":"限时折扣","price_bp_month":600,"price_bp_forever":2500},"current_sources":null,"finish_sources":null,"sale_left_time":152155,"sale_time_end":-1668779045,"sale_surplus":19997,"sale_count_desc":"","tag":"正在预约","suit_items":{"card":[{"item_id":40587,"name":"蛋酒一家","state":"inactive","tab_id":35,"suit_item_id":40665,"properties":{"gray_rule":"false","hot":"false","image":"https://i0.hdslb.com/bfs/garb/item/e99fb9eccb486c9c1d97095e655cb3148e504de4.png","realname_auth":"false","sale_type":"other"},"current_activity":null,"current_sources":null,"finish_sources":null,"sale_left_time":-1668779045,"sale_time_end":-1668779045,"sale_surplus":0,"items":null},{"item_id":40588,"name":"蛋酒一家粉丝","state":"inactive","tab_id":35,"suit_item_id":40665,"properties":{"gray_rule":"false","hot":"false","image":"https://i0.hdslb.com/bfs/garb/item/8790188be21ede0e931bcdf3ba14eedd6cccd8bf.png","image_preview_small":"https://i0.hdslb.com/bfs/garb/item/158afdea0aa5e43faffc603915ec2a089919d5af.png","realname_auth":"false","sale_type":"other"},"current_activity":null,"current_sources":null,"finish_sources":null,"sale_left_time":-1668779045,"sale_time_end":-1668779045,"sale_surplus":0,"items":null}],"card_bg":[{"item_id":40637,"name":"蛋酒一家","state":"active","tab_id":44,"suit_item_id":40665,"properties":{"gray_rule":"false","image":"https://i0.hdslb.com/bfs/garb/item/e9cbc5516de2c3a64b078a60de4b991fc72ebfb8.png","image_preview_small":"https://i0.hdslb.com/bfs/garb/item/d21f7544768057ccb80b46628fe157370b4aaa62.png","realname_auth":"false","sale_type":"suit"},"current_activity":null,"current_sources":null,"finish_sources":null,"sale_left_time":-1668779045,"sale_time_end":-1668779045,"sale_surplus":0,"items":null}],"emoji_package":[{"item_id":40595,"name":"蛋酒一家","state":"active","tab_id":8,"suit_item_id":40665,"properties":{"addable":"true","biz":"dynamic,reply,watch_full","gray_rule":"false","image":"http://i0.hdslb.com/bfs/emote/c7fbec37cc3bcef75ded1e0be006b63e8c67b773.png","is_symbol":"false","item_ids":"40592,40606,40607,40608,40609,40610,40611,40612,40613,40614,40615,40616,40617,40618,40619,40620,40621,40622,40623,40624,40625,40626,40627,40628,40629,40630,40631,40633,40663,40664","permanent":"false","preview":"false","realname_auth":"false","recently_used":"false","recommend":"false","ref_mid":"0","removable":"true","sale_type":"pay","setting_pannel_not_show":"false","size":"L","sortable":"true"},"current_activity":null,"current_sources":null,"finish_sources":null,"sale_left_time":-1668779045,"sale_time_end":-1668779045,"sale_surplus":0,"items":[{"item_id":40592,"name":"[蛋酒一家_送心]","state":"active","tab_id":7,"suit_item_id":0,"properties":{"associate":"false","gray_rule":"false","image":"http://i0.hdslb.com/bfs/emote/a3db6ab1609aa93ad2b943a77c1fe2dc103122d6.png","is_symbol":"false","ref_mid":"0","sale_type":"pay"},"current_activity":null,"current_sources":null,"finish_sources":null,"sale_left_time":-1668779045,"sale_time_end":-1668779045,"sale_surplus":0},{"item_id":40606,"name":"[蛋酒一家_啊对对对]","state":"active","tab_id":7,"suit_item_id":0,"properties":{"associate":"false","gray_rule":"false","image":"http://i0.hdslb.com/bfs/emote/9ebf108743eee375a2092fbb4b73f5f9324872c7.png","is_symbol":"false","ref_mid":"0","sale_type":"pay"},"current_activity":null,"current_sources":null,"finish_sources":null,"sale_left_time":-1668779045,"sale_time_end":-1668779045,"sale_surplus":0},{"item_id":40607,"name":"[蛋酒一家_阿巴]","state":"active","tab_id":7,"suit_item_id":0,"properties":{"associate":"false","gray_rule":"false","image":"http://i0.hdslb.com/bfs/emote/22af2a087e9d8ba35357fa4d11362d00163336c4.png","is_symbol":"false","ref_mid":"0","sale_type":"pay"},"current_activity":null,"current_sources":null,"finish_sources":null,"sale_left_time":-1668779045,"sale_time_end":-1668779045,"sale_surplus":0},{"item_id":40608,"name":"[蛋酒一家_emo]","state":"active","tab_id":7,"suit_item_id":0,"properties":{"associate":"false","gray_rule":"false","image":"http://i0.hdslb.com/bfs/emote/2287ef934fa2850bc45120296ced73eec1e60026.png","is_symbol":"false","ref_mid":"0","sale_type":"pay"},"current_activity":null,"current_sources":null,"finish_sources":null,"sale_left_time":-1668779045,"sale_time_end":-1668779045,"sale_surplus":0},{"item_id":40609,"name":"[蛋酒一家_水枪攻击]","state":"active","tab_id":7,"suit_item_id":0,"properties":{"associate":"false","gray_rule":"false","image":"http://i0.hdslb.com/bfs/emote/8a7e2b4e9a92ee364fd6d555f4e50ce2215f6332.png","is_symbol":"false","ref_mid":"0","sale_type":"pay"},"current_activity":null,"current_sources":null,"finish_sources":null,"sale_left_time":-1668779045,"sale_time_end":-1668779045,"sale_surplus":0},{"item_id":40610,"name":"[蛋酒一家_抬杠]","state":"active","tab_id":7,"suit_item_id":0,"properties":{"associate":"false","gray_rule":"false","image":"http://i0.hdslb.com/bfs/emote/7d7c50dc52642dae85244a54e8729fa76703c0e2.png","is_symbol":"false","ref_mid":"0","sale_type":"pay"},"current_activity":null,"current_sources":null,"finish_sources":null,"sale_left_time":-1668779045,"sale_time_end":-1668779045,"sale_surplus":0},{"item_id":40611,"name":"[蛋酒一家_赞啊]","state":"active","tab_id":7,"suit_item_id":0,"properties":{"associate":"false","gray_rule":"false","image":"http://i0.hdslb.com/bfs/emote/95918aa3f443cc731989e635c4c69b1d058a891e.png","is_symbol":"false","ref_mid":"0","sale_type":"pay"},"current_activity":null,"current_sources":null,"finish_sources":null,"sale_left_time":-1668779045,"sale_time_end":-1668779045,"sale_surplus":0},{"item_id":40612,"name":"[蛋酒一家_看你洗]","state":"active","tab_id":7,"suit_item_id":0,"properties":{"associate":"false","gray_rule":"false","image":"http://i0.hdslb.com/bfs/emote/41d7bdb904992cfc3e40a5df0fa10355f82d7c65.png","is_symbol":"false","ref_mid":"0","sale_type":"pay"},"current_activity":null,"current_sources":null,"finish_sources":null,"sale_left_time":-1668779045,"sale_time_end":-1668779045,"sale_surplus":0},{"item_id":40613,"name":"[蛋酒一家_伤心]","state":"active","tab_id":7,"suit_item_id":0,"properties":{"associate":"false","gray_rule":"false","image":"http://i0.hdslb.com/bfs/emote/eb09e6f0b062e7811595d193e466553f4f46bea3.png","is_symbol":"false","ref_mid":"0","sale_type":"pay"},"current_activity":null,"current_sources":null,"finish_sources":null,"sale_left_time":-1668779045,"sale_time_end":-1668779045,"sale_surplus":0},{"item_id":40614,"name":"[蛋酒一家_上火]","state":"active","tab_id":7,"suit_item_id":0,"properties":{"associate":"false","gray_rule":"false","image":"http://i0.hdslb.com/bfs/emote/743d12d19549071dc1e7de2c08e26ae7e79c8d2d.png","is_symbol":"false","ref_mid":"0","sale_type":"pay"},"current_activity":null,"current_sources":null,"finish_sources":null,"sale_left_time":-1668779045,"sale_time_end":-1668779045,"sale_surplus":0},{"item_id":40615,"name":"[蛋酒一家_帮你灭火]","state":"active","tab_id":7,"suit_item_id":0,"properties":{"associate":"false","gray_rule":"false","image":"http://i0.hdslb.com/bfs/emote/a9f9aac68c67463e890da4de693efe0bfaca24c2.png","is_symbol":"false","ref_mid":"0","sale_type":"pay"},"current_activity":null,"current_sources":null,"finish_sources":null,"sale_left_time":-1668779045,"sale_time_end":-1668779045,"sale_surplus":0},{"item_id":40616,"name":"[蛋酒一家_往这看]","state":"active","tab_id":7,"suit_item_id":0,"properties":{"associate":"false","gray_rule":"false","image":"http://i0.hdslb.com/bfs/emote/bc444024acd3bf4afb1f2637dab052dcb323bd46.png","is_symbol":"false","ref_mid":"0","sale_type":"pay"},"current_activity":null,"current_sources":null,"finish_sources":null,"sale_left_time":-1668779045,"sale_time_end":-1668779045,"sale_surplus":0},{"item_id":40617,"name":"[蛋酒一家_知道了]","state":"active","tab_id":7,"suit_item_id":0,"properties":{"associate":"false","gray_rule":"false","image":"http://i0.hdslb.com/bfs/emote/9599d724537cd49f792dbc1631ab49b533797065.png","is_symbol":"false","ref_mid":"0","sale_type":"pay"},"current_activity":null,"current_sources":null,"finish_sources":null,"sale_left_time":-1668779045,"sale_time_end":-1668779045,"sale_surplus":0},{"item_id":40618,"name":"[蛋酒一家_达成共识]","state":"active","tab_id":7,"suit_item_id":0,"properties":{"associate":"false","gray_rule":"false","image":"http://i0.hdslb.com/bfs/emote/c079a89eba140b53520ecda53b94ef0b8d3cd75e.png","is_symbol":"false","ref_mid":"0","sale_type":"pay"},"current_activity":null,"current_sources":null,"finish_sources":null,"sale_left_time":-1668779045,"sale_time_end":-1668779045,"sale_surplus":0},{"item_id":40619,"name":"[蛋酒一家_我丢]","state":"active","tab_id":7,"suit_item_id":0,"properties":{"associate":"false","gray_rule":"false","image":"http://i0.hdslb.com/bfs/emote/659f6911af9c6e55613c3c4c0017a44dfc1ccf11.png","is_symbol":"false","ref_mid":"0","sale_type":"pay"},"current_activity":null,"current_sources":null,"finish_sources":null,"sale_left_time":-1668779045,"sale_time_end":-1668779045,"sale_surplus":0},{"item_id":40620,"name":"[蛋酒一家_锤你]","state":"active","tab_id":7,"suit_item_id":0,"properties":{"associate":"false","gray_rule":"false","image":"http://i0.hdslb.com/bfs/emote/e10b9829a01d820fc008bbc0a14945257ad09eb5.png","is_symbol":"false","ref_mid":"0","sale_type":"pay"},"current_activity":null,"current_sources":null,"finish_sources":null,"sale_left_time":-1668779045,"sale_time_end":-1668779045,"sale_surplus":0},{"item_id":40621,"name":"[蛋酒一家_流口水]","state":"active","tab_id":7,"suit_item_id":0,"properties":{"associate":"false","gray_rule":"false","image":"http://i0.hdslb.com/bfs/emote/34d3a904e05819f9b50b062b4afce67c68a498c0.png","is_symbol":"false","ref_mid":"0","sale_type":"pay"},"current_activity":null,"current_sources":null,"finish_sources":null,"sale_left_time":-1668779045,"sale_time_end":-1668779045,"sale_surplus":0},{"item_id":40622,"name":"[蛋酒一家_尬住]","state":"active","tab_id":7,"suit_item_id":0,"properties":{"associate":"false","gray_rule":"false","image":"http://i0.hdslb.com/bfs/emote/637b95d7edf4eebaa79560fab08b15e68c5a7b5c.png","is_symbol":"false","ref_mid":"0","sale_type":"pay"},"current_activity":null,"current_sources":null,"finish_sources":null,"sale_left_time":-1668779045,"sale_time_end":-1668779045,"sale_surplus":0},{"item_id":40623,"name":"[蛋酒一家_大佬]","state":"active","tab_id":7,"suit_item_id":0,"properties":{"associate":"false","gray_rule":"false","image":"http://i0.hdslb.com/bfs/emote/349e4304f9879f5e5fb7d120a640bf01a3223211.png","is_symbol":"false","ref_mid":"0","sale_type":"pay"},"current_activity":null,"current_sources":null,"finish_sources":null,"sale_left_time":-1668779045,"sale_time_end":-1668779045,"sale_surplus":0},{"item_id":40624,"name":"[蛋酒一家_？]","state":"active","tab_id":7,"suit_item_id":0,"properties":{"associate":"false","gray_rule":"false","image":"http://i0.hdslb.com/bfs/emote/9d7c63f29d679b1321a495ba9a84ee0e38cc9317.png","is_symbol":"false","ref_mid":"0","sale_type":"pay"},"current_activity":null,"current_sources":null,"finish_sources":null,"sale_left_time":-1668779045,"sale_time_end":-1668779045,"sale_surplus":0},{"item_id":40625,"name":"[蛋酒一家_冲啊]","state":"active","tab_id":7,"suit_item_id":0,"properties":{"associate":"false","gray_rule":"false","image":"http://i0.hdslb.com/bfs/emote/db5110e27f4ba6ec208648da01bf13b908b0bb92.png","is_symbol":"false","ref_mid":"0","sale_type":"pay"},"current_activity":null,"current_sources":null,"finish_sources":null,"sale_left_time":-1668779045,"sale_time_end":-1668779045,"sale_surplus":0},{"item_id":40626,"name":"[蛋酒一家_好耶]","state":"active","tab_id":7,"suit_item_id":0,"properties":{"associate":"false","gray_rule":"false","image":"http://i0.hdslb.com/bfs/emote/610e5f892a73bc9869371a0ce9a7cfa0f3466e8e.png","is_symbol":"false","ref_mid":"0","sale_type":"pay"},"current_activity":null,"current_sources":null,"finish_sources":null,"sale_left_time":-1668779045,"sale_time_end":-1668779045,"sale_surplus":0},{"item_id":40627,"name":"[蛋酒一家_有内鬼]","state":"active","tab_id":7,"suit_item_id":0,"properties":{"associate":"false","gray_rule":"false","image":"http://i0.hdslb.com/bfs/emote/428ccde6d4f55d12799cfeff6404fee8b2fe266b.png","is_symbol":"false","ref_mid":"0","sale_type":"pay"},"current_activity":null,"current_sources":null,"finish_sources":null,"sale_left_time":-1668779045,"sale_time_end":-1668779045,"sale_surplus":0},{"item_id":40628,"name":"[蛋酒一家_溜了]","state":"active","tab_id":7,"suit_item_id":0,"properties":{"associate":"false","gray_rule":"false","image":"http://i0.hdslb.com/bfs/emote/703ac4f75fc71439307df4492b7240aa109138d0.png","is_symbol":"false","ref_mid":"0","sale_type":"pay"},"current_activity":null,"current_sources":null,"finish_sources":null,"sale_left_time":-1668779045,"sale_time_end":-1668779045,"sale_surplus":0},{"item_id":40629,"name":"[蛋酒一家_电锯警告]","state":"active","tab_id":7,"suit_item_id":0,"properties":{"associate":"false","gray_rule":"false","image":"http://i0.hdslb.com/bfs/emote/0f85fab81577877f444931e6f4fdf3c0449fa50a.png","is_symbol":"false","ref_mid":"0","sale_type":"pay"},"current_activity":null,"current_sources":null,"finish_sources":null,"sale_left_time":-1668779045,"sale_time_end":-1668779045,"sale_surplus":0},{"item_id":40630,"name":"[蛋酒一家_假笑]","state":"active","tab_id":7,"suit_item_id":0,"properties":{"associate":"false","gray_rule":"false","image":"http://i0.hdslb.com/bfs/emote/663c0375e3642e7bbe0679d37eabf5e414cd6624.png","is_symbol":"false","ref_mid":"0","sale_type":"pay"},"current_activity":null,"current_sources":null,"finish_sources":null,"sale_left_time":-1668779045,"sale_time_end":-1668779045,"sale_surplus":0},{"item_id":40631,"name":"[蛋酒一家_霸屏]","state":"active","tab_id":7,"suit_item_id":0,"properties":{"associate":"false","gray_rule":"false","image":"http://i0.hdslb.com/bfs/emote/2d268d421c5a8f75631cb29dae2ea93b244b911a.png","is_symbol":"false","ref_mid":"0","sale_type":"pay"},"current_activity":null,"current_sources":null,"finish_sources":null,"sale_left_time":-1668779045,"sale_time_end":-1668779045,"sale_surplus":0},{"item_id":40633,"name":"[蛋酒一家_盯上你了]","state":"active","tab_id":7,"suit_item_id":0,"properties":{"associate":"false","gray_rule":"false","image":"http://i0.hdslb.com/bfs/emote/c581aa34d2cd9854fda0abbdb84515e5ce08e584.png","is_symbol":"false","ref_mid":"0","sale_type":"pay"},"current_activity":null,"current_sources":null,"finish_sources":null,"sale_left_time":-1668779045,"sale_time_end":-1668779045,"sale_surplus":0},{"item_id":40663,"name":"[蛋酒一家_警告]","state":"active","tab_id":7,"suit_item_id":0,"properties":{"associate":"false","gray_rule":"false","image":"http://i0.hdslb.com/bfs/emote/6f37c53bde9aac0a056b37e18fa73153f5a5a97f.png","is_symbol":"false","ref_mid":"0","sale_type":"pay"},"current_activity":null,"current_sources":null,"finish_sources":null,"sale_left_time":-1668779045,"sale_time_end":-1668779045,"sale_surplus":0},{"item_id":40664,"name":"[蛋酒一家_tui]","state":"active","tab_id":7,"suit_item_id":0,"properties":{"associate":"false","gray_rule":"false","image":"http://i0.hdslb.com/bfs/emote/cc78c835fe6f06db982ccda1dedc1afca30d2789.png","is_symbol":"false","ref_mid":"0","sale_type":"pay"},"current_activity":null,"current_sources":null,"finish_sources":null,"sale_left_time":-1668779045,"sale_time_end":-1668779045,"sale_surplus":0}]}],"skin":[{"item_id":40662,"name":"蛋酒一家","state":"active","tab_id":45,"suit_item_id":40665,"properties":{"color":"#ffffff","color_mode":"dark","color_second_page":"#5a4ba9","gray_rule":"false","head_bg":"https://i0.hdslb.com/bfs/garb/item/c10e2d24fa60939d12aaf7e0c676b66b30c6c0ec.jpg","head_myself_mp4_play":"once","head_myself_squared_bg":"https://i0.hdslb.com/bfs/garb/item/684d752592e8b3abb876bb1c8691224d3355cb21.jpg","head_tab_bg":"https://i0.hdslb.com/bfs/garb/item/2290015c63d47dc86ff90a5ab1ee9d240b42f712.jpg","image_cover":"https://i0.hdslb.com/bfs/garb/item/7f4aa66794a7c4b9f4f99a3fd0ba6beb96877f51.jpg","image_preview":"https://i0.hdslb.com/bfs/garb/item/9dab1a37b554a94730e22cc9e1a3f1b2670b77db.jpg","package_md5":"d0ecc9b91cb7261129ea1528bb00d5d2","package_url":"https://i0.hdslb.com/bfs/garb/zip/087c43bb561c032082d262de51f78cfc0f865805.zip","realname_auth":"false","skin_mode":"normal","tail_bg":"https://i0.hdslb.com/bfs/garb/item/3789b5e1e3bbf6f99766951aad5c3e0677ac69b9.png","tail_color":"#ffffff","tail_color_selected":"#ffde84","tail_icon_ani":"true","tail_icon_ani_mode":"once","tail_icon_channel":"https://i0.hdslb.com/bfs/garb/item/d69b9a03ce8894745e353efe80e7e8871dbc0100.png","tail_icon_dynamic":"https://i0.hdslb.com/bfs/garb/item/4cd0b403a30cdfe58018c43849e20e009cff4c84.png","tail_icon_main":"https://i0.hdslb.com/bfs/garb/item/a938d971dc706b3af0357c1eb0797b4b3c3a012b.png","tail_icon_mode":"img","tail_icon_myself":"https://i0.hdslb.com/bfs/garb/item/0a473a95ae14d82dd292f15c4ccc7932a9e497cc.png","tail_icon_pub_btn_bg":"https://i0.hdslb.com/bfs/garb/item/4cd0b403a30cdfe58018c43849e20e009cff4c84.png","tail_icon_selected_channel":"https://i0.hdslb.com/bfs/garb/item/1d1dabfe480d2bc61a0e38924ad81f818800a8ec.png","tail_icon_selected_dynamic":"https://i0.hdslb.com/bfs/garb/item/d78d7b36b5db8e533704f2f2ee9c10d5b9f12e1e.png","tail_icon_selected_main":"https://i0.hdslb.com/bfs/garb/item/bc0758d76b806e299878483f6f6b9f7d481be37d.png","tail_icon_selected_myself":"https://i0.hdslb.com/bfs/garb/item/35bac17a97e26ebff079b6a019e73dc28c0a3f56.png","tail_icon_selected_pub_btn_bg":"https://i0.hdslb.com/bfs/garb/item/d78d7b36b5db8e533704f2f2ee9c10d5b9f12e1e.png","tail_icon_selected_shop":"https://i0.hdslb.com/bfs/garb/item/12d704cd133f27346e3ba496ddf63f2b7b50588c.png","tail_icon_shop":"https://i0.hdslb.com/bfs/garb/item/e876b708f58d7ea6c6385308eab20f8f7dff54b8.png","ver":"1668762736"},"current_activity":null,"current_sources":null,"finish_sources":null,"sale_left_time":-1668779045,"sale_time_end":-1668779045,"sale_surplus":0,"items":null}],"space_bg":[{"item_id":40635,"name":"蛋酒一家","state":"active","tab_id":37,"suit_item_id":40665,"properties":{"fan_no_color":"#21abea","fan_no_image":"https://i0.hdslb.com/bfs/garb/item/e6ec85f85ecf7883589365db4581f12e4d31f5ab.png","gray_rule":"false","image1_landscape":"https://i0.hdslb.com/bfs/garb/item/6fd39b881e1b33baedc767a93806fbba678b86d5.png","image1_portrait":"https://i0.hdslb.com/bfs/garb/item/841b87100b741714e687a686601ba6330e56cc13.png","realname_auth":"false"},"current_activity":null,"current_sources":null,"finish_sources":null,"sale_left_time":-1668779045,"sale_time_end":-1668779045,"sale_surplus":0,"items":null}]},"fan_user":{"mid":504406727,"nickname":"顶晟无线","avatar":"https://i2.hdslb.com/bfs/face/ba8b71a8a4c85695845a40326b6d2f6aded49f92.jpg"},"unlock_items":null,"activity_entrance":{"id":0,"item_id":0,"title":"","image_cover":"","jump_link":""}}}